README
setup.py
distarkcli/__init__.py
distarkcli.egg-info/PKG-INFO
distarkcli.egg-info/SOURCES.txt
distarkcli.egg-info/dependency_links.txt
distarkcli.egg-info/not-zip-safe
distarkcli.egg-info/top_level.txt
distarkcli/protos/__init__.py
distarkcli/protos/generic_service_pb2.py
distarkcli/protos/objects/__init__.py
distarkcli/protos/objects/food_pb2.py
distarkcli/protos/services/__init__.py
distarkcli/protos/services/another_service_pb2.py
distarkcli/protos/services/search_food_service_pb2.py
distarkcli/protos/services/simple_service_pb2.py
distarkcli/services/__init__.py
distarkcli/services/anotherservice.py
distarkcli/services/searchfoodservice.py
distarkcli/services/simpleservice.py
distarkcli/transport/__init__.py
distarkcli/transport/distarkclient.py
distarkcli/transport/majordomoclient.py
distarkcli/transport/transportpool.py
distarkcli/utils/MDP.py
distarkcli/utils/MyConfiguration.py
distarkcli/utils/NetInfo.py
distarkcli/utils/PBUtils.py
distarkcli/utils/__init__.py
distarkcli/utils/uniq.py
distarkcli/utils/zhelpers.py
distarkcli/utils/zoo.py