Metadata-Version: 1.0
Name: distarkcli
Version: 0.5
Summary: Booya?
Home-page: http://github.com/GustavePate/distarkcli
Author: Gustave Pate
Author-email: flyingcircus@example.com
License: MIT
Platform: UNKNOWN
